alifedata_phyloinformatics_convert/RosettaTree.py
alifedata_phyloinformatics_convert/__init__.py
alifedata_phyloinformatics_convert/__main__.py
alifedata_phyloinformatics_convert/alife_dataframe_to_biopython_tree.py
alifedata_phyloinformatics_convert/alife_dataframe_to_biopython_trees.py
alifedata_phyloinformatics_convert/alife_dataframe_to_dendropy_tree.py
alifedata_phyloinformatics_convert/alife_dataframe_to_dendropy_trees.py
alifedata_phyloinformatics_convert/alife_dataframe_to_dict_of_lists.py
alifedata_phyloinformatics_convert/alife_dataframe_to_ete_tree.py
alifedata_phyloinformatics_convert/alife_dataframe_to_ete_trees.py
alifedata_phyloinformatics_convert/alife_dataframe_to_networkx_digraph.py
alifedata_phyloinformatics_convert/alife_dataframe_to_phylotrack_systematics.py
alifedata_phyloinformatics_convert/alife_dataframe_to_treeswift_tree.py
alifedata_phyloinformatics_convert/alife_dataframe_to_treeswift_trees.py
alifedata_phyloinformatics_convert/anytree_tree_to_alife_dataframe.py
alifedata_phyloinformatics_convert/biopython_tree_to_alife_dataframe.py
alifedata_phyloinformatics_convert/cli.py
alifedata_phyloinformatics_convert/dendropy_tree_to_alife_dataframe.py
alifedata_phyloinformatics_convert/dendropy_tree_to_scipy_linkage_matrix.py
alifedata_phyloinformatics_convert/ete_tree_to_alife_dataframe.py
alifedata_phyloinformatics_convert/networkx_digraph_to_alife_dataframe.py
alifedata_phyloinformatics_convert/phylotrack_systematics_to_alife_dataframe.py
alifedata_phyloinformatics_convert/scipy_linkage_matrix_to_dendropy_tree.py
alifedata_phyloinformatics_convert/treeswift_tree_to_alife_dataframe.py
alifedata_phyloinformatics_convert/_impl/__init__.py
alifedata_phyloinformatics_convert/_impl/alifestd_is_asexual.py
alifedata_phyloinformatics_convert/_impl/alifestd_is_sexual.py
alifedata_phyloinformatics_convert/_impl/alifestd_make_ancestor_id_col.py
alifedata_phyloinformatics_convert/_impl/alifestd_make_ancestor_list_col.py
alifedata_phyloinformatics_convert-0.19.0.dist-info/AUTHORS.rst
alifedata_phyloinformatics_convert-0.19.0.dist-info/LICENSE
alifedata_phyloinformatics_convert-0.19.0.dist-info/METADATA
alifedata_phyloinformatics_convert-0.19.0.dist-info/WHEEL
alifedata_phyloinformatics_convert-0.19.0.dist-info/entry_points.txt
alifedata_phyloinformatics_convert-0.19.0.dist-info/top_level.txt
alifedata_phyloinformatics_convert-0.19.0.dist-info/RECORD
