Metadata-Version: 2.1
Name: alifedata-phyloinformatics-convert
Version: 0.19.0
Summary: alifedata-phyloinformatics-convert helps apply traditional phyloinformatics software to alife standardized data
Home-page: https://github.com/mmore500/alifedata-phyloinformatics-convert
Author: Matthew Andres Moreno
Author-email: m.more500@gmail.com
License: MIT license
Keywords: alifedata-phyloinformatics-convert
Platform: UNKNOWN
Classifier: Development Status :: 2 - Pre-Alpha
Classifier: Intended Audience :: Developers
Classifier: License :: OSI Approved :: MIT License
Classifier: Natural Language :: English
Classifier: Programming Language :: Python :: 3
Classifier: Programming Language :: Python :: 3.8
Classifier: Programming Language :: Python :: 3.9
Classifier: Programming Language :: Python :: 3.10
Classifier: Programming Language :: Python :: 3.11
Classifier: Programming Language :: Python :: 3.12
Classifier: Programming Language :: Python :: 3.13
Requires-Python: >=3.8
Requires-Dist: anytree>=2.8.0
Requires-Dist: biopython>=1.79
Requires-Dist: click>=7.0
Requires-Dist: dendropy>=5.0.0
Requires-Dist: Deprecated>=1.2.13
Requires-Dist: ete3>=3.0.0
Requires-Dist: iterpop>=0.4.0
Requires-Dist: nanto>=0.1.1
Requires-Dist: networkx>=2.5
Requires-Dist: numpy>=1.21.5
Requires-Dist: opytional>=0.1.0
Requires-Dist: pandas>=1.1.0
Requires-Dist: sortedcontainers>=2.4.0
Requires-Dist: treeswift
Requires-Dist: typing-extensions>=4.7.1
Requires-Dist: validators>=0.20.0
Requires-Dist: yarl>=1.9.3
Provides-Extra: docs
Requires-Dist: sphinx; extra == "docs"
Requires-Dist: alabaster; extra == "docs"
Requires-Dist: twine==1.14.0; extra == "docs"
Requires-Dist: mkdocs==1.2.3; extra == "docs"
Requires-Dist: jinja2==3.0.0; extra == "docs"
Provides-Extra: test
Requires-Dist: pytest>=3; extra == "test"
Requires-Dist: phylotrackpy>=0.1.16; extra == "test"
